openstack/__init__.py
openstack/__main__.py
openstack/_log.py
openstack/_services_mixin.py
openstack/connection.py
openstack/exceptions.py
openstack/fields.py
openstack/format.py
openstack/proxy.py
openstack/py.typed
openstack/resource.py
openstack/service_description.py
openstack/types.py
openstack/utils.py
openstack/version.py
openstack/warnings.py
openstack/_hacking/checks.py
openstack/accelerator/__init__.py
openstack/accelerator/accelerator_service.py
openstack/accelerator/version.py
openstack/accelerator/v2/__init__.py
openstack/accelerator/v2/_proxy.py
openstack/accelerator/v2/accelerator_request.py
openstack/accelerator/v2/attribute.py
openstack/accelerator/v2/deployable.py
openstack/accelerator/v2/device.py
openstack/accelerator/v2/device_profile.py
openstack/baremetal/__init__.py
openstack/baremetal/baremetal_service.py
openstack/baremetal/configdrive.py
openstack/baremetal/version.py
openstack/baremetal/v1/__init__.py
openstack/baremetal/v1/_common.py
openstack/baremetal/v1/_proxy.py
openstack/baremetal/v1/allocation.py
openstack/baremetal/v1/chassis.py
openstack/baremetal/v1/conductor.py
openstack/baremetal/v1/deploy_templates.py
openstack/baremetal/v1/driver.py
openstack/baremetal/v1/inspection_rules.py
openstack/baremetal/v1/node.py
openstack/baremetal/v1/port.py
openstack/baremetal/v1/port_group.py
openstack/baremetal/v1/runbooks.py
openstack/baremetal/v1/volume_connector.py
openstack/baremetal/v1/volume_target.py
openstack/baremetal_introspection/__init__.py
openstack/baremetal_introspection/baremetal_introspection_service.py
openstack/baremetal_introspection/v1/__init__.py
openstack/baremetal_introspection/v1/_proxy.py
openstack/baremetal_introspection/v1/introspection.py
openstack/baremetal_introspection/v1/introspection_rule.py
openstack/block_storage/__init__.py
openstack/block_storage/block_storage_service.py
openstack/block_storage/v2/__init__.py
openstack/block_storage/v2/_proxy.py
openstack/block_storage/v2/backup.py
openstacksdk-4.9.0.dist-info/licenses/AUTHORS
openstacksdk-4.9.0.dist-info/licenses/LICENSE
openstacksdk-4.9.0.dist-info/METADATA
openstacksdk-4.9.0.dist-info/WHEEL
openstacksdk-4.9.0.dist-info/entry_points.txt
openstacksdk-4.9.0.dist-info/pbr.json
openstacksdk-4.9.0.dist-info/top_level.txt
openstacksdk-4.9.0.dist-info/RECORD
